pybpodgui_plugin_waveplayer/__init__.py
pybpodgui_plugin_waveplayer/module.py
pybpodgui_plugin_waveplayer/module_api.py
pybpodgui_plugin_waveplayer/module_gui.py
pybpodgui_plugin_waveplayer/settings.py
pybpodgui_plugin_waveplayer/models/__init__.py
pybpodgui_plugin_waveplayer/models/projects/__init__.py
pybpodgui_plugin_waveplayer/models/projects/projects_waveplayer.py
pybpod_gui_plugin_waveplayer-1.0.dist-info/METADATA
pybpod_gui_plugin_waveplayer-1.0.dist-info/WHEEL
pybpod_gui_plugin_waveplayer-1.0.dist-info/top_level.txt
pybpod_gui_plugin_waveplayer-1.0.dist-info/RECORD
